glassnode/__init__.py
glassnode/consts.py
glassnode/exceptions.py
glassnode/glassnode_client.py
tests/__init__.py
tests/test_glassnode.py
tests/utils.py
glassnode-0.0.2.dist-info/LICENSE
glassnode-0.0.2.dist-info/METADATA
glassnode-0.0.2.dist-info/WHEEL
glassnode-0.0.2.dist-info/top_level.txt
glassnode-0.0.2.dist-info/RECORD
