Metadata-Version: 2.1
Name: glassnode
Version: 0.0.2
Summary: Glassnode API client for python
Home-page: https://github.com/anselumana/glassnode-python-api
Author: Ansel Umana
Author-email: anselumana.developer@gmail.com
License: UNKNOWN
Project-URL: Bug Tracker, https://github.com/anselumana/glassnode-python-api/issues
Platform: UNKNOWN
Classifier: Programming Language :: Python :: 3
Classifier: License :: OSI Approved :: MIT License
Classifier: Operating System :: OS Independent
Requires-Python: >=3.6
License-File: LICENSE
